[
    {
        "scenario": "BasicDataCapture",
        "input variable": [
            {
                "clock cycles": 4,
                "d": [
                    "00000000",
                    "11111111",
                    "10101010",
                    "01010101"
                ]
            }
        ]
    },
    {
        "scenario": "AlternatingBitPatterns",
        "input variable": [
            {
                "clock cycles": 6,
                "d": [
                    "01010101",
                    "10101010",
                    "01010101",
                    "10101010",
                    "01010101",
                    "10101010"
                ]
            }
        ]
    },
    {
        "scenario": "WalkingOnesPattern",
        "input variable": [
            {
                "clock cycles": 8,
                "d": [
                    "00000001",
                    "00000010",
                    "00000100",
                    "00001000",
                    "00010000",
                    "00100000",
                    "01000000",
                    "10000000"
                ]
            }
        ]
    },
    {
        "scenario": "WalkingZerosPattern",
        "input variable": [
            {
                "clock cycles": 8,
                "d": [
                    "11111110",
                    "11111101",
                    "11111011",
                    "11110111",
                    "11101111",
                    "11011111",
                    "10111111",
                    "01111111"
                ]
            }
        ]
    },
    {
        "scenario": "SetupTimeVerification",
        "input variable": [
            {
                "clock cycles": 4,
                "d": [
                    "11110000",
                    "00001111",
                    "11001100",
                    "00110011"
                ]
            }
        ]
    },
    {
        "scenario": "HoldTimeVerification",
        "input variable": [
            {
                "clock cycles": 4,
                "d": [
                    "11001100",
                    "00110011",
                    "11110000",
                    "00001111"
                ]
            }
        ]
    },
    {
        "scenario": "MultipleClockCyclesStability",
        "input variable": [
            {
                "clock cycles": 5,
                "d": [
                    "10101010",
                    "10101010",
                    "10101010",
                    "10101010",
                    "10101010"
                ]
            }
        ]
    },
    {
        "scenario": "HighFrequencyOperation",
        "input variable": [
            {
                "clock cycles": 8,
                "d": [
                    "11111111",
                    "00000000",
                    "11111111",
                    "00000000",
                    "11111111",
                    "00000000",
                    "11111111",
                    "00000000"
                ]
            }
        ]
    }
]