[
    {
        "scenario": "InitialValueCheck",
        "input variable": [
            {
                "clock cycles": 4,
                "a": [
                    "1",
                    "1",
                    "1",
                    "1"
                ]
            }
        ]
    },
    {
        "scenario": "FixedValueOperation",
        "input variable": [
            {
                "clock cycles": 8,
                "a": [
                    "1",
                    "1",
                    "1",
                    "1",
                    "1",
                    "1",
                    "1",
                    "1"
                ]
            }
        ]
    },
    {
        "scenario": "StartCountingSequence",
        "input variable": [
            {
                "clock cycles": 6,
                "a": [
                    "1",
                    "1",
                    "0",
                    "0",
                    "0",
                    "0"
                ]
            }
        ]
    },
    {
        "scenario": "CounterRollover",
        "input variable": [
            {
                "clock cycles": 8,
                "a": [
                    "0",
                    "0",
                    "0",
                    "0",
                    "0",
                    "0",
                    "0",
                    "0"
                ]
            }
        ]
    },
    {
        "scenario": "StopCountingOperation",
        "input variable": [
            {
                "clock cycles": 6,
                "a": [
                    "0",
                    "0",
                    "0",
                    "1",
                    "1",
                    "1"
                ]
            }
        ]
    },
    {
        "scenario": "MultipleCountingCycles",
        "input variable": [
            {
                "clock cycles": 12,
                "a": [
                    "1",
                    "1",
                    "0",
                    "0",
                    "0",
                    "0",
                    "1",
                    "1",
                    "0",
                    "0",
                    "0",
                    "0"
                ]
            }
        ]
    }
]